.gitignore
AUTHORS.rst
CHANGES.rst
README.rst
development.ini
setup.py
docs/.gitignore
docs/Makefile
docs/conf.py
kotti_accounts/__init__.py
kotti_accounts/tests.py
kotti_accounts/views.py
kotti_accounts.egg-info/PKG-INFO
kotti_accounts.egg-info/SOURCES.txt
kotti_accounts.egg-info/dependency_links.txt
kotti_accounts.egg-info/not-zip-safe
kotti_accounts.egg-info/requires.txt
kotti_accounts.egg-info/top_level.txt
kotti_accounts/templates/edit/accounts.pt