Metadata-Version: 1.1
Name: kotti-accounts
Version: 0.2.5
Summary: Allows a user principal to be associated to multiple email accounts.
Home-page: http://kotti_accounts.readthedocs.org
Author: Richard Gomes
Author-email: rgomes.info@gmail.com
License: BSD
Keywords: pyramid kotti user account management
Platform: UNKNOWN
Classifier: Environment :: Web Environment
Classifier: Framework :: Pylons
Classifier: Framework :: Pyramid
Classifier: Intended Audience :: Developers
Classifier: License :: OSI Approved :: BSD License
Classifier: Operating System :: OS Independent
Classifier: Programming Language :: Python
Classifier: Programming Language :: Python :: 2.6
Classifier: Programming Language :: Python :: 2.7
Classifier: Topic :: Internet :: WWW/HTTP
Classifier: Topic :: Internet :: WWW/HTTP :: Dynamic Content
Classifier: Topic :: Internet :: WWW/HTTP :: WSGI :: Application
Classifier: Topic :: Software Development :: User Interfaces
